YehuoIMxRtKuKaifaShizhanZhinan/README.md
YehuoIMxRtKuKaifaShizhanZhinan/__init__.py
YehuoIMxRtKuKaifaShizhanZhinan/__main__.py
YehuoIMxRtKuKaifaShizhanZhinan/file.epub
YehuoIMxRtKuKaifaShizhanZhinan/index.html
YehuoIMxRtKuKaifaShizhanZhinan/css/__init__.py
YehuoIMxRtKuKaifaShizhanZhinan/css/annotations.css
YehuoIMxRtKuKaifaShizhanZhinan/css/main.css
YehuoIMxRtKuKaifaShizhanZhinan/css/normalize.css
YehuoIMxRtKuKaifaShizhanZhinan/css/popup.css
YehuoIMxRtKuKaifaShizhanZhinan/font/__init__.py
YehuoIMxRtKuKaifaShizhanZhinan/font/fontello.eot
YehuoIMxRtKuKaifaShizhanZhinan/font/fontello.svg
YehuoIMxRtKuKaifaShizhanZhinan/font/fontello.ttf
YehuoIMxRtKuKaifaShizhanZhinan/font/fontello.woff
YehuoIMxRtKuKaifaShizhanZhinan/img/__init__.py
YehuoIMxRtKuKaifaShizhanZhinan/img/annotator-glyph-sprite.png
YehuoIMxRtKuKaifaShizhanZhinan/img/annotator-icon-sprite.png
YehuoIMxRtKuKaifaShizhanZhinan/img/apple-touch-icon.png
YehuoIMxRtKuKaifaShizhanZhinan/img/cancelfullscreen.png
YehuoIMxRtKuKaifaShizhanZhinan/img/close.png
YehuoIMxRtKuKaifaShizhanZhinan/img/fullscreen.png
YehuoIMxRtKuKaifaShizhanZhinan/img/loader.gif
YehuoIMxRtKuKaifaShizhanZhinan/img/menu-icon.png
YehuoIMxRtKuKaifaShizhanZhinan/img/save.png
YehuoIMxRtKuKaifaShizhanZhinan/img/saved.png
YehuoIMxRtKuKaifaShizhanZhinan/img/settings-s.png
YehuoIMxRtKuKaifaShizhanZhinan/img/settings.png
YehuoIMxRtKuKaifaShizhanZhinan/img/star.png
YehuoIMxRtKuKaifaShizhanZhinan/js/__init__.py
YehuoIMxRtKuKaifaShizhanZhinan/js/epub.js
YehuoIMxRtKuKaifaShizhanZhinan/js/epub.min.js
YehuoIMxRtKuKaifaShizhanZhinan/js/epub.min.map
YehuoIMxRtKuKaifaShizhanZhinan/js/hooks.min.js
YehuoIMxRtKuKaifaShizhanZhinan/js/hooks.min.map
YehuoIMxRtKuKaifaShizhanZhinan/js/reader.js
YehuoIMxRtKuKaifaShizhanZhinan/js/reader.js.map
YehuoIMxRtKuKaifaShizhanZhinan/js/reader.min.js
YehuoIMxRtKuKaifaShizhanZhinan/js/reader.min.map
YehuoIMxRtKuKaifaShizhanZhinan/js/hooks/__init__.py
YehuoIMxRtKuKaifaShizhanZhinan/js/hooks/extensions/__init__.py
yehuo_i_mx_rt_ku_kaifa_shizhan_zhinan-2024.3.5.0.dist-info/METADATA
yehuo_i_mx_rt_ku_kaifa_shizhan_zhinan-2024.3.5.0.dist-info/WHEEL
yehuo_i_mx_rt_ku_kaifa_shizhan_zhinan-2024.3.5.0.dist-info/entry_points.txt
yehuo_i_mx_rt_ku_kaifa_shizhan_zhinan-2024.3.5.0.dist-info/top_level.txt
yehuo_i_mx_rt_ku_kaifa_shizhan_zhinan-2024.3.5.0.dist-info/RECORD
